{"v":"5.12.1","fr":24,"ip":76,"op":172,"w":500,"h":500,"nm":"Lokaal geproduceerd - Lottiiieee","ddd":0,"assets":[{"id":"comp_0","nm":"Lokaal geproduceerd","fr":24,"layers":[{"ddd":0,"ind":1,"ty":3,"nm":"▣ Void 1","parent":18,"sr":1,"ks":{"o":{"a":0,"k":100,"ix":11},"r":{"a":1,"k":[{"i":{"x":[0.91],"y":[1]},"o":{"x":[0.751],"y":[0]},"t":-10,"s":[-15]},{"i":{"x":[0.607],"y":[0.274]},"o":{"x":[0.748],"y":[0]},"t":64,"s":[-11]},{"i":{"x":[0.667],"y":[1]},"o":{"x":[0.495],"y":[-0.365]},"t":76,"s":[-13.752]},{"i":{"x":[0.667],"y":[1]},"o":{"x":[0.281],"y":[0]},"t":86,"s":[-8]},{"t":96,"s":[-15]}],"ix":10},"p":{"a":0,"k":[-0.247,-45.573,0],"ix":2,"l":2},"a":{"a":0,"k":[0,0,0],"ix":1,"l":2},"s":{"a":0,"k":[50,50,100],"ix":6,"l":2}},"ao":0,"ef":[{"ty":5,"nm":"Void","np":19,"mn":"Pseudo/250958","ix":1,"en":1,"ef":[{"ty":0,"nm":"Width","mn":"Pseudo/250958-0001","ix":1,"v":{"a":0,"k":100,"ix":1}},{"ty":0,"nm":"Height","mn":"Pseudo/250958-0002","ix":2,"v":{"a":0,"k":100,"ix":2}},{"ty":0,"nm":"Offset X","mn":"Pseudo/250958-0003","ix":3,"v":{"a":0,"k":0,"ix":3}},{"ty":0,"nm":"Offset Y","mn":"Pseudo/250958-0004","ix":4,"v":{"a":0,"k":0,"ix":4}},{"ty":0,"nm":"Roundness","mn":"Pseudo/250958-0005","ix":5,"v":{"a":0,"k":0,"ix":5}},{"ty":6,"nm":"About","mn":"Pseudo/250958-0006","ix":6,"v":0},{"ty":6,"nm":"Plague of null layers.","mn":"Pseudo/250958-0007","ix":7,"v":0},{"ty":6,"nm":"Void","mn":"Pseudo/250958-0008","ix":8,"v":0},{"ty":6,"nm":"Following projects","mn":"Pseudo/250958-0009","ix":9,"v":0},{"ty":6,"nm":"Void","mn":"Pseudo/250958-0010","ix":10,"v":0},{"ty":6,"nm":"through time.","mn":"Pseudo/250958-0011","ix":11,"v":0},{"ty":6,"nm":"Void","mn":"Pseudo/250958-0012","ix":12,"v":0},{"ty":6,"nm":"Be free of the past.","mn":"Pseudo/250958-0013","ix":13,"v":0},{"ty":6,"nm":"Void","mn":"Pseudo/250958-0014","ix":14,"v":0},{"ty":6,"nm":"Copyright 2023 Battle Axe Inc","mn":"Pseudo/250958-0015","ix":15,"v":0},{"ty":6,"nm":"Void","mn":"Pseudo/250958-0016","ix":16,"v":0},{"ty":6,"nm":"Void","mn":"Pseudo/250958-0017","ix":17,"v":0}]}],"ip":0,"op":96,"st":0,"ct":1,"bm":0},{"ddd":0,"ind":2,"ty":4,"nm":"Tulp Dashes","parent":1,"sr":1,"ks":{"o":{"a":1,"k":[{"i":{"x":[0.833],"y":[0.833]},"o":{"x":[0.167],"y":[0.167]},"t":14,"s":[100]},{"i":{"x":[0.833],"y":[0.833]},"o":{"x":[0.167],"y":[0.167]},"t":15,"s":[0]},{"i":{"x":[0.833],"y":[0.833]},"o":{"x":[0.167],"y":[0.167]},"t":82,"s":[0]},{"t":83,"s":[100]}],"ix":11},"r":{"a":1,"k":[{"i":{"x":[0.833],"y":[1]},"o":{"x":[0.167],"y":[0.167]},"t":15,"s":[15]},{"i":{"x":[0.6],"y":[1]},"o":{"x":[0.32],"y":[0.94]},"t":82,"s":[45]},{"t":88,"s":[15]}],"ix":10},"p":{"a":1,"k":[{"i":{"x":0.833,"y":1},"o":{"x":0.167,"y":0.167},"t":15,"s":[19.5,-70.5,0],"to":[0,0,0],"ti":[0,0,0]},{"i":{"x":0.6,"y":1},"o":{"x":0.32,"y":0.94},"t":82,"s":[28,-64.5,0],"to":[0,0,0],"ti":[0,0,0]},{"t":88,"s":[19.5,-70.5,0]}],"ix":2,"l":2},"a":{"a":0,"k":[0,0,0],"ix":1,"l":2},"s":{"a":0,"k":[200,200,100],"ix":6,"l":2}},"ao":0,"hasMask":true,"masksProperties":[{"inv":false,"mode":"s","pt":{"a":0,"k":{"i":[[0,0],[0,0],[0,0],[0,0]],"o":[[0,0],[0,0],[0,0],[0,0]],"v":[[48.116,-2.022],[-37.232,0.141],[-42.308,51.712],[42.855,42.093]],"c":true},"ix":1},"o":{"a":0,"k":100,"ix":3},"x":{"a":0,"k":0,"ix":4},"nm":"Mask 1"}],"shapes":[{"ty":"gr","it":[{"ind":0,"ty":"sh","ix":1,"ks":{"a":0,"k":{"i":[[0,0],[0,0],[-1.664,-15.729],[-14.696,0],[0,0],[-0.44,13.345]],"o":[[0,0],[0,0],[1.664,15.729],[0,0],[14.696,0],[0.44,-13.345]],"v":[[0.126,-43.815],[0.001,-43.677],[-26.61,9.979],[0,36.589],[0,36.589],[26.61,9.979]],"c":true},"ix":2},"nm":"Path 1","mn":"ADBE Vector Shape - Group","hd":false},{"ty":"st","c":{"a":0,"k":[0,0.388235300779,0.466666668653,1],"ix":3},"o":{"a":0,"k":100,"ix":4},"w":{"a":0,"k":1.897,"ix":5},"lc":1,"lj":1,"ml":10,"bm":0,"d":[{"n":"d","nm":"dash","v":{"a":0,"k":10,"ix":1}},{"n":"o","nm":"offset","v":{"a":0,"k":0,"ix":7}}],"nm":"Stroke 1","mn":"ADBE Vector Graphic - Stroke","hd":false},{"ty":"tr","p":{"a":0,"k":[0,0],"ix":2},"a":{"a":0,"k":[0,0],"ix":1},"s":{"a":0,"k":[100,100],"ix":3},"r":{"a":0,"k":0,"ix":6},"o":{"a":0,"k":100,"ix":7},"sk":{"a":0,"k":0,"ix":4},"sa":{"a":0,"k":0,"ix":5},"nm":"Transform"}],"nm":"Lokaal geproduceerd","np":3,"cix":2,"bm":0,"ix":1,"mn":"ADBE Vector Group","hd":false}],"ip":0,"op":96,"st":0,"ct":1,"bm":0},{"ddd":0,"ind":3,"ty":4,"nm":"Tulp Dashes 2","parent":1,"sr":1,"ks":{"o":{"a":1,"k":[{"i":{"x":[0.833],"y":[0.833]},"o":{"x":[0.167],"y":[0.167]},"t":14,"s":[100]},{"i":{"x":[0.833],"y":[0.833]},"o":{"x":[0.167],"y":[0.167]},"t":15,"s":[0]},{"i":{"x":[0.833],"y":[0.833]},"o":{"x":[0.167],"y":[0.167]},"t":82,"s":[0]},{"t":83,"s":[100]}],"ix":11},"r":{"a":1,"k":[{"i":{"x":[0.833],"y":[1]},"o":{"x":[0.167],"y":[0.167]},"t":15,"s":[15]},{"i":{"x":[0.6],"y":[1]},"o":{"x":[0.32],"y":[0.94]},"t":82,"s":[45]},{"t":88,"s":[15]}],"ix":10},"p":{"a":1,"k":[{"i":{"x":0.833,"y":1},"o":{"x":0.167,"y":0.167},"t":15,"s":[19.5,-70.5,0],"to":[0,0,0],"ti":[0,0,0]},{"i":{"x":0.6,"y":1},"o":{"x":0.32,"y":0.94},"t":82,"s":[28,-64.5,0],"to":[0,0,0],"ti":[0,0,0]},{"t":88,"s":[19.5,-70.5,0]}],"ix":2,"l":2},"a":{"a":0,"k":[0,0,0],"ix":1,"l":2},"s":{"a":0,"k":[200,200,100],"ix":6,"l":2}},"ao":0,"hasMask":true,"masksProperties":[{"inv":false,"mode":"s","pt":{"a":0,"k":{"i":[[0,0],[0,0],[0,0],[0,0]],"o":[[0,0],[0,0],[0,0],[0,0]],"v":[[48.116,-2.022],[-37.232,0.141],[-42.308,51.712],[42.855,42.093]],"c":true},"ix":1},"o":{"a":0,"k":100,"ix":3},"x":{"a":0,"k":0,"ix":4},"nm":"Mask 1"}],"shapes":[{"ty":"gr","it":[{"ind":0,"ty":"sh","ix":1,"ks":{"a":0,"k":{"i":[[0,0],[0,0],[-1.664,-15.729],[-14.696,0],[0,0],[-0.44,13.345]],"o":[[0,0],[0,0],[1.664,15.729],[0,0],[14.696,0],[0.44,-13.345]],"v":[[0.126,-43.815],[0.001,-43.677],[-26.61,9.979],[0,36.589],[0,36.589],[26.61,9.979]],"c":true},"ix":2},"nm":"Path 1","mn":"ADBE Vector Shape - Group","hd":false},{"ty":"st","c":{"a":0,"k":[0,0.388235300779,0.466666668653,1],"ix":3},"o":{"a":0,"k":100,"ix":4},"w":{"a":0,"k":1.897,"ix":5},"lc":1,"lj":1,"ml":10,"bm":0,"d":[{"n":"d","nm":"dash","v":{"a":0,"k":10,"ix":1}},{"n":"o","nm":"offset","v":{"a":0,"k":0,"ix":7}}],"nm":"Stroke 1","mn":"ADBE Vector Graphic - Stroke","hd":false},{"ty":"fl","c":{"a":0,"k":[1,1,1,1],"ix":4},"o":{"a":0,"k":100,"ix":5},"r":1,"bm":0,"nm":"Fill 1","mn":"ADBE Vector Graphic - Fill","hd":false},{"ty":"tr","p":{"a":0,"k":[0,0],"ix":2},"a":{"a":0,"k":[0,0],"ix":1},"s":{"a":0,"k":[100,100],"ix":3},"r":{"a":0,"k":0,"ix":6},"o":{"a":0,"k":100,"ix":7},"sk":{"a":0,"k":0,"ix":4},"sa":{"a":0,"k":0,"ix":5},"nm":"Transform"}],"nm":"Lokaal geproduceerd","np":3,"cix":2,"bm":0,"ix":1,"mn":"ADBE Vector Group","hd":false}],"ip":0,"op":96,"st":0,"ct":1,"bm":0},{"ddd":0,"ind":4,"ty":4,"nm":"Tulp R","parent":1,"sr":1,"ks":{"o":{"a":0,"k":100,"ix":11},"r":{"a":1,"k":[{"i":{"x":[0.2],"y":[1]},"o":{"x":[0.6],"y":[0.1]},"t":18,"s":[15]},{"i":{"x":[0.833],"y":[1]},"o":{"x":[0.167],"y":[0]},"t":30,"s":[45]},{"i":{"x":[0.6],"y":[1]},"o":{"x":[0.32],"y":[0.94]},"t":82,"s":[45]},{"t":88,"s":[15]}],"ix":10},"p":{"a":1,"k":[{"i":{"x":0.2,"y":1},"o":{"x":0.6,"y":0.05},"t":18,"s":[19.5,-70.5,0],"to":[0,0,0],"ti":[0,0,0]},{"i":{"x":0.833,"y":0.833},"o":{"x":0.167,"y":0.167},"t":30,"s":[28,-64.5,0],"to":[0,0,0],"ti":[0,0,0]},{"i":{"x":0.6,"y":1},"o":{"x":0.32,"y":0.94},"t":82,"s":[28,-64.5,0],"to":[0,0,0],"ti":[0,0,0]},{"t":88,"s":[19.5,-70.5,0]}],"ix":2,"l":2},"a":{"a":0,"k":[0,0,0],"ix":1,"l":2},"s":{"a":0,"k":[200,200,100],"ix":6,"l":2}},"ao":0,"shapes":[{"ty":"gr","it":[{"ind":0,"ty":"sh","ix":1,"ks":{"a":1,"k":[{"i":{"x":0.2,"y":1},"o":{"x":0.6,"y":0.1},"t":6,"s":[{"i":[[0,0],[0,0],[0,0],[-14.696,0],[0,0],[0,14.696]],"o":[[0,0],[0,0],[0,14.696],[0,0],[14.696,0],[0,0]],"v":[[26.842,-44.416],[-26.378,-44.416],[-26.61,9.979],[0,36.589],[0,36.589],[26.61,9.979]],"c":true}]},{"i":{"x":0.833,"y":1},"o":{"x":0.167,"y":0},"t":18,"s":[{"i":[[0,0],[0,0],[-1.664,-15.729],[-14.696,0],[0,0],[-0.44,13.345]],"o":[[0,0],[0,0],[1.664,15.729],[0,0],[14.696,0],[0.44,-13.345]],"v":[[0.126,-43.815],[0.001,-43.677],[-26.61,9.979],[0,36.589],[0,36.589],[26.61,9.979]],"c":true}]},{"i":{"x":0.6,"y":1},"o":{"x":0.32,"y":0.94},"t":82,"s":[{"i":[[0,0],[0,0],[-1.664,-15.729],[-14.696,0],[0,0],[-0.44,13.345]],"o":[[0,0],[0,0],[1.664,15.729],[0,0],[14.696,0],[0.44,-13.345]],"v":[[0.126,-43.815],[0.001,-43.677],[-26.61,9.979],[0,36.589],[0,36.589],[26.61,9.979]],"c":true}]},{"t":88,"s":[{"i":[[0,0],[0,0],[0,0],[-14.696,0],[0,0],[0,14.696]],"o":[[0,0],[0,0],[0,14.696],[0,0],[14.696,0],[0,0]],"v":[[26.842,-44.416],[-26.378,-44.416],[-26.61,9.979],[0,36.589],[0,36.589],[26.61,9.979]],"c":true}]}],"ix":2},"nm":"Path 1","mn":"ADBE Vector Shape - Group","hd":false},{"ty":"st","c":{"a":0,"k":[0,0.388235300779,0.466666668653,1],"ix":3},"o":{"a":0,"k":100,"ix":4},"w":{"a":0,"k":1.897,"ix":5},"lc":1,"lj":1,"ml":10,"bm":0,"nm":"Stroke 1","mn":"ADBE Vector Graphic - Stroke","hd":false},{"ty":"tr","p":{"a":0,"k":[0,0],"ix":2},"a":{"a":0,"k":[0,0],"ix":1},"s":{"a":0,"k":[100,100],"ix":3},"r":{"a":0,"k":0,"ix":6},"o":{"a":0,"k":100,"ix":7},"sk":{"a":0,"k":0,"ix":4},"sa":{"a":0,"k":0,"ix":5},"nm":"Transform"}],"nm":"Lokaal geproduceerd","np":3,"cix":2,"bm":0,"ix":1,"mn":"ADBE Vector Group","hd":false}],"ip":0,"op":96,"st":0,"ct":1,"bm":0},{"ddd":0,"ind":5,"ty":4,"nm":"Tulp R 2","parent":1,"sr":1,"ks":{"o":{"a":0,"k":100,"ix":11},"r":{"a":1,"k":[{"i":{"x":[0.2],"y":[1]},"o":{"x":[0.6],"y":[0.1]},"t":18,"s":[15]},{"i":{"x":[0.833],"y":[1]},"o":{"x":[0.167],"y":[0]},"t":30,"s":[45]},{"i":{"x":[0.6],"y":[1]},"o":{"x":[0.32],"y":[0.94]},"t":82,"s":[45]},{"t":88,"s":[15]}],"ix":10},"p":{"a":1,"k":[{"i":{"x":0.2,"y":1},"o":{"x":0.6,"y":0.05},"t":18,"s":[19.5,-70.5,0],"to":[0,0,0],"ti":[0,0,0]},{"i":{"x":0.833,"y":0.833},"o":{"x":0.167,"y":0.167},"t":30,"s":[28,-64.5,0],"to":[0,0,0],"ti":[0,0,0]},{"i":{"x":0.6,"y":1},"o":{"x":0.32,"y":0.94},"t":82,"s":[28,-64.5,0],"to":[0,0,0],"ti":[0,0,0]},{"t":88,"s":[19.5,-70.5,0]}],"ix":2,"l":2},"a":{"a":0,"k":[0,0,0],"ix":1,"l":2},"s":{"a":0,"k":[200,200,100],"ix":6,"l":2}},"ao":0,"shapes":[{"ty":"gr","it":[{"ind":0,"ty":"sh","ix":1,"ks":{"a":1,"k":[{"i":{"x":0.2,"y":1},"o":{"x":0.6,"y":0.1},"t":6,"s":[{"i":[[0,0],[0,0],[0,0],[-14.696,0],[0,0],[0,14.696]],"o":[[0,0],[0,0],[0,14.696],[0,0],[14.696,0],[0,0]],"v":[[26.842,-44.416],[-26.378,-44.416],[-26.61,9.979],[0,36.589],[0,36.589],[26.61,9.979]],"c":true}]},{"i":{"x":0.833,"y":1},"o":{"x":0.167,"y":0},"t":18,"s":[{"i":[[0,0],[0,0],[-1.664,-15.729],[-14.696,0],[0,0],[-0.44,13.345]],"o":[[0,0],[0,0],[1.664,15.729],[0,0],[14.696,0],[0.44,-13.345]],"v":[[0.126,-43.815],[0.001,-43.677],[-26.61,9.979],[0,36.589],[0,36.589],[26.61,9.979]],"c":true}]},{"i":{"x":0.6,"y":1},"o":{"x":0.32,"y":0.94},"t":82,"s":[{"i":[[0,0],[0,0],[-1.664,-15.729],[-14.696,0],[0,0],[-0.44,13.345]],"o":[[0,0],[0,0],[1.664,15.729],[0,0],[14.696,0],[0.44,-13.345]],"v":[[0.126,-43.815],[0.001,-43.677],[-26.61,9.979],[0,36.589],[0,36.589],[26.61,9.979]],"c":true}]},{"t":88,"s":[{"i":[[0,0],[0,0],[0,0],[-14.696,0],[0,0],[0,14.696]],"o":[[0,0],[0,0],[0,14.696],[0,0],[14.696,0],[0,0]],"v":[[26.842,-44.416],[-26.378,-44.416],[-26.61,9.979],[0,36.589],[0,36.589],[26.61,9.979]],"c":true}]}],"ix":2},"nm":"Path 1","mn":"ADBE Vector Shape - Group","hd":false},{"ty":"st","c":{"a":0,"k":[0,0.388235300779,0.466666668653,1],"ix":3},"o":{"a":0,"k":100,"ix":4},"w":{"a":0,"k":1.897,"ix":5},"lc":1,"lj":1,"ml":10,"bm":0,"nm":"Stroke 1","mn":"ADBE Vector Graphic - Stroke","hd":false},{"ty":"fl","c":{"a":0,"k":[1,1,1,1],"ix":4},"o":{"a":0,"k":100,"ix":5},"r":1,"bm":0,"nm":"Fill 1","mn":"ADBE Vector Graphic - Fill","hd":false},{"ty":"tr","p":{"a":0,"k":[0,0],"ix":2},"a":{"a":0,"k":[0,0],"ix":1},"s":{"a":0,"k":[100,100],"ix":3},"r":{"a":0,"k":0,"ix":6},"o":{"a":0,"k":100,"ix":7},"sk":{"a":0,"k":0,"ix":4},"sa":{"a":0,"k":0,"ix":5},"nm":"Transform"}],"nm":"Lokaal geproduceerd","np":3,"cix":2,"bm":0,"ix":1,"mn":"ADBE Vector Group","hd":false}],"ip":0,"op":96,"st":0,"ct":1,"bm":0},{"ddd":0,"ind":6,"ty":4,"nm":"Tulp L Dashes","parent":1,"sr":1,"ks":{"o":{"a":1,"k":[{"i":{"x":[0.833],"y":[0.833]},"o":{"x":[0.167],"y":[0.167]},"t":38,"s":[100]},{"i":{"x":[0.833],"y":[0.833]},"o":{"x":[0.167],"y":[0.167]},"t":39,"s":[0]},{"i":{"x":[0.833],"y":[0.833]},"o":{"x":[0.167],"y":[0.167]},"t":80,"s":[0]},{"t":81,"s":[100]}],"ix":11},"r":{"a":1,"k":[{"i":{"x":[0.833],"y":[1]},"o":{"x":[0.167],"y":[0.167]},"t":39,"s":[15]},{"i":{"x":[0.6],"y":[1]},"o":{"x":[0.32],"y":[0.94]},"t":80,"s":[-15]},{"t":86,"s":[15]}],"ix":10},"p":{"a":1,"k":[{"i":{"x":0.833,"y":1},"o":{"x":0.167,"y":0.167},"t":39,"s":[19.5,-70.5,0],"to":[0,0,0],"ti":[0,0,0]},{"i":{"x":0.6,"y":1},"o":{"x":0.32,"y":0.94},"t":80,"s":[8.5,-73.5,0],"to":[0,0,0],"ti":[0,0,0]},{"t":86,"s":[19.5,-70.5,0]}],"ix":2,"l":2},"a":{"a":0,"k":[0,0,0],"ix":1,"l":2},"s":{"a":0,"k":[200,200,100],"ix":6,"l":2}},"ao":0,"shapes":[{"ty":"gr","it":[{"ind":0,"ty":"sh","ix":1,"ks":{"a":0,"k":{"i":[[0,0],[0,0],[-1.664,-15.729],[-14.696,0],[0,0],[-0.44,13.345]],"o":[[0,0],[0,0],[1.664,15.729],[0,0],[14.696,0],[0.44,-13.345]],"v":[[0.381,-42.024],[0.256,-41.887],[-26.61,9.979],[0,36.589],[0,36.589],[26.61,9.979]],"c":true},"ix":2},"nm":"Path 1","mn":"ADBE Vector Shape - Group","hd":false},{"ty":"st","c":{"a":0,"k":[0,0.388235300779,0.466666668653,1],"ix":3},"o":{"a":0,"k":100,"ix":4},"w":{"a":0,"k":1.897,"ix":5},"lc":1,"lj":1,"ml":10,"bm":0,"d":[{"n":"d","nm":"dash","v":{"a":0,"k":10,"ix":1}},{"n":"o","nm":"offset","v":{"a":0,"k":0,"ix":7}}],"nm":"Stroke 1","mn":"ADBE Vector Graphic - Stroke","hd":false},{"ty":"tr","p":{"a":0,"k":[0,0],"ix":2},"a":{"a":0,"k":[0,0],"ix":1},"s":{"a":0,"k":[100,100],"ix":3},"r":{"a":0,"k":0,"ix":6},"o":{"a":0,"k":100,"ix":7},"sk":{"a":0,"k":0,"ix":4},"sa":{"a":0,"k":0,"ix":5},"nm":"Transform"}],"nm":"Lokaal geproduceerd","np":3,"cix":2,"bm":0,"ix":1,"mn":"ADBE Vector Group","hd":false}],"ip":0,"op":96,"st":0,"ct":1,"bm":0},{"ddd":0,"ind":7,"ty":4,"nm":"Tulp L Dashes 2","parent":1,"sr":1,"ks":{"o":{"a":1,"k":[{"i":{"x":[0.833],"y":[0.833]},"o":{"x":[0.167],"y":[0.167]},"t":38,"s":[100]},{"i":{"x":[0.833],"y":[0.833]},"o":{"x":[0.167],"y":[0.167]},"t":39,"s":[0]},{"i":{"x":[0.833],"y":[0.833]},"o":{"x":[0.167],"y":[0.167]},"t":80,"s":[0]},{"t":81,"s":[100]}],"ix":11},"r":{"a":1,"k":[{"i":{"x":[0.833],"y":[1]},"o":{"x":[0.167],"y":[0.167]},"t":39,"s":[15]},{"i":{"x":[0.6],"y":[1]},"o":{"x":[0.32],"y":[0.94]},"t":80,"s":[-15]},{"t":86,"s":[15]}],"ix":10},"p":{"a":1,"k":[{"i":{"x":0.833,"y":1},"o":{"x":0.167,"y":0.167},"t":39,"s":[19.5,-70.5,0],"to":[0,0,0],"ti":[0,0,0]},{"i":{"x":0.6,"y":1},"o":{"x":0.32,"y":0.94},"t":80,"s":[8.5,-73.5,0],"to":[0,0,0],"ti":[0,0,0]},{"t":86,"s":[19.5,-70.5,0]}],"ix":2,"l":2},"a":{"a":0,"k":[0,0,0],"ix":1,"l":2},"s":{"a":0,"k":[200,200,100],"ix":6,"l":2}},"ao":0,"shapes":[{"ty":"gr","it":[{"ind":0,"ty":"sh","ix":1,"ks":{"a":0,"k":{"i":[[0,0],[0,0],[-1.664,-15.729],[-14.696,0],[0,0],[-0.44,13.345]],"o":[[0,0],[0,0],[1.664,15.729],[0,0],[14.696,0],[0.44,-13.345]],"v":[[0.381,-42.024],[0.256,-41.887],[-26.61,9.979],[0,36.589],[0,36.589],[26.61,9.979]],"c":true},"ix":2},"nm":"Path 1","mn":"ADBE Vector Shape - Group","hd":false},{"ty":"st","c":{"a":0,"k":[0,0.388235300779,0.466666668653,1],"ix":3},"o":{"a":0,"k":100,"ix":4},"w":{"a":0,"k":1.897,"ix":5},"lc":1,"lj":1,"ml":10,"bm":0,"d":[{"n":"d","nm":"dash","v":{"a":0,"k":10,"ix":1}},{"n":"o","nm":"offset","v":{"a":0,"k":0,"ix":7}}],"nm":"Stroke 1","mn":"ADBE Vector Graphic - Stroke","hd":false},{"ty":"fl","c":{"a":0,"k":[1,1,1,1],"ix":4},"o":{"a":0,"k":100,"ix":5},"r":1,"bm":0,"nm":"Fill 1","mn":"ADBE Vector Graphic - Fill","hd":false},{"ty":"tr","p":{"a":0,"k":[0,0],"ix":2},"a":{"a":0,"k":[0,0],"ix":1},"s":{"a":0,"k":[100,100],"ix":3},"r":{"a":0,"k":0,"ix":6},"o":{"a":0,"k":100,"ix":7},"sk":{"a":0,"k":0,"ix":4},"sa":{"a":0,"k":0,"ix":5},"nm":"Transform"}],"nm":"Lokaal geproduceerd","np":3,"cix":2,"bm":0,"ix":1,"mn":"ADBE Vector Group","hd":false}],"ip":0,"op":96,"st":0,"ct":1,"bm":0},{"ddd":0,"ind":8,"ty":4,"nm":"Tulp L","parent":1,"sr":1,"ks":{"o":{"a":0,"k":100,"ix":11},"r":{"a":1,"k":[{"i":{"x":[0.2],"y":[1]},"o":{"x":[0.6],"y":[0.1]},"t":42,"s":[15]},{"i":{"x":[0.833],"y":[1]},"o":{"x":[0.167],"y":[0]},"t":54,"s":[-15]},{"i":{"x":[0.6],"y":[1]},"o":{"x":[0.32],"y":[0.94]},"t":80,"s":[-15]},{"t":86,"s":[15]}],"ix":10},"p":{"a":1,"k":[{"i":{"x":0.2,"y":1},"o":{"x":0.6,"y":0.05},"t":42,"s":[19.5,-70.5,0],"to":[0,0,0],"ti":[0,0,0]},{"i":{"x":0.833,"y":0.833},"o":{"x":0.167,"y":0.167},"t":54,"s":[8.5,-73.5,0],"to":[0,0,0],"ti":[0,0,0]},{"i":{"x":0.6,"y":1},"o":{"x":0.32,"y":0.94},"t":80,"s":[8.5,-73.5,0],"to":[0,0,0],"ti":[0,0,0]},{"t":86,"s":[19.5,-70.5,0]}],"ix":2,"l":2},"a":{"a":0,"k":[0,0,0],"ix":1,"l":2},"s":{"a":0,"k":[200,200,100],"ix":6,"l":2}},"ao":0,"shapes":[{"ty":"gr","it":[{"ind":0,"ty":"sh","ix":1,"ks":{"a":1,"k":[{"i":{"x":0.2,"y":1},"o":{"x":0.6,"y":0.1},"t":30,"s":[{"i":[[0,0],[0,0],[0,0],[-14.696,0],[0,0],[0,14.696]],"o":[[0,0],[0,0],[0,14.696],[0,0],[14.696,0],[0,0]],"v":[[27.054,-42.661],[-26.166,-42.661],[-26.61,9.979],[0,36.589],[0,36.589],[26.61,9.979]],"c":true}]},{"i":{"x":0.833,"y":1},"o":{"x":0.167,"y":0},"t":42,"s":[{"i":[[0,0],[0,0],[-1.664,-15.729],[-14.696,0],[0,0],[-0.44,13.345]],"o":[[0,0],[0,0],[1.664,15.729],[0,0],[14.696,0],[0.44,-13.345]],"v":[[0.381,-42.024],[0.256,-41.887],[-26.61,9.979],[0,36.589],[0,36.589],[26.61,9.979]],"c":true}]},{"i":{"x":0.6,"y":1},"o":{"x":0.32,"y":0.94},"t":80,"s":[{"i":[[0,0],[0,0],[-1.664,-15.729],[-14.696,0],[0,0],[-0.44,13.345]],"o":[[0,0],[0,0],[1.664,15.729],[0,0],[14.696,0],[0.44,-13.345]],"v":[[0.381,-42.024],[0.256,-41.887],[-26.61,9.979],[0,36.589],[0,36.589],[26.61,9.979]],"c":true}]},{"t":86,"s":[{"i":[[0,0],[0,0],[0,0],[-14.696,0],[0,0],[0,14.696]],"o":[[0,0],[0,0],[0,14.696],[0,0],[14.696,0],[0,0]],"v":[[27.054,-42.661],[-26.166,-42.661],[-26.61,9.979],[0,36.589],[0,36.589],[26.61,9.979]],"c":true}]}],"ix":2},"nm":"Path 1","mn":"ADBE Vector Shape - Group","hd":false},{"ty":"st","c":{"a":0,"k":[0,0.388235300779,0.466666668653,1],"ix":3},"o":{"a":0,"k":100,"ix":4},"w":{"a":0,"k":1.897,"ix":5},"lc":1,"lj":1,"ml":10,"bm":0,"nm":"Stroke 1","mn":"ADBE Vector Graphic - Stroke","hd":false},{"ty":"tr","p":{"a":0,"k":[0,0],"ix":2},"a":{"a":0,"k":[0,0],"ix":1},"s":{"a":0,"k":[100,100],"ix":3},"r":{"a":0,"k":0,"ix":6},"o":{"a":0,"k":100,"ix":7},"sk":{"a":0,"k":0,"ix":4},"sa":{"a":0,"k":0,"ix":5},"nm":"Transform"}],"nm":"Lokaal geproduceerd","np":3,"cix":2,"bm":0,"ix":1,"mn":"ADBE Vector Group","hd":false}],"ip":0,"op":96,"st":0,"ct":1,"bm":0},{"ddd":0,"ind":9,"ty":4,"nm":"Tulp L 2","parent":1,"sr":1,"ks":{"o":{"a":0,"k":100,"ix":11},"r":{"a":1,"k":[{"i":{"x":[0.2],"y":[1]},"o":{"x":[0.6],"y":[0.1]},"t":42,"s":[15]},{"i":{"x":[0.833],"y":[1]},"o":{"x":[0.167],"y":[0]},"t":54,"s":[-15]},{"i":{"x":[0.6],"y":[1]},"o":{"x":[0.32],"y":[0.94]},"t":80,"s":[-15]},{"t":86,"s":[15]}],"ix":10},"p":{"a":1,"k":[{"i":{"x":0.2,"y":1},"o":{"x":0.6,"y":0.05},"t":42,"s":[19.5,-70.5,0],"to":[0,0,0],"ti":[0,0,0]},{"i":{"x":0.833,"y":0.833},"o":{"x":0.167,"y":0.167},"t":54,"s":[8.5,-73.5,0],"to":[0,0,0],"ti":[0,0,0]},{"i":{"x":0.6,"y":1},"o":{"x":0.32,"y":0.94},"t":80,"s":[8.5,-73.5,0],"to":[0,0,0],"ti":[0,0,0]},{"t":86,"s":[19.5,-70.5,0]}],"ix":2,"l":2},"a":{"a":0,"k":[0,0,0],"ix":1,"l":2},"s":{"a":0,"k":[200,200,100],"ix":6,"l":2}},"ao":0,"shapes":[{"ty":"gr","it":[{"ind":0,"ty":"sh","ix":1,"ks":{"a":1,"k":[{"i":{"x":0.2,"y":1},"o":{"x":0.6,"y":0.1},"t":30,"s":[{"i":[[0,0],[0,0],[0,0],[-14.696,0],[0,0],[0,14.696]],"o":[[0,0],[0,0],[0,14.696],[0,0],[14.696,0],[0,0]],"v":[[27.054,-42.661],[-26.166,-42.661],[-26.61,9.979],[0,36.589],[0,36.589],[26.61,9.979]],"c":true}]},{"i":{"x":0.833,"y":1},"o":{"x":0.167,"y":0},"t":42,"s":[{"i":[[0,0],[0,0],[-1.664,-15.729],[-14.696,0],[0,0],[-0.44,13.345]],"o":[[0,0],[0,0],[1.664,15.729],[0,0],[14.696,0],[0.44,-13.345]],"v":[[0.381,-42.024],[0.256,-41.887],[-26.61,9.979],[0,36.589],[0,36.589],[26.61,9.979]],"c":true}]},{"i":{"x":0.6,"y":1},"o":{"x":0.32,"y":0.94},"t":80,"s":[{"i":[[0,0],[0,0],[-1.664,-15.729],[-14.696,0],[0,0],[-0.44,13.345]],"o":[[0,0],[0,0],[1.664,15.729],[0,0],[14.696,0],[0.44,-13.345]],"v":[[0.381,-42.024],[0.256,-41.887],[-26.61,9.979],[0,36.589],[0,36.589],[26.61,9.979]],"c":true}]},{"t":86,"s":[{"i":[[0,0],[0,0],[0,0],[-14.696,0],[0,0],[0,14.696]],"o":[[0,0],[0,0],[0,14.696],[0,0],[14.696,0],[0,0]],"v":[[27.054,-42.661],[-26.166,-42.661],[-26.61,9.979],[0,36.589],[0,36.589],[26.61,9.979]],"c":true}]}],"ix":2},"nm":"Path 1","mn":"ADBE Vector Shape - Group","hd":false},{"ty":"st","c":{"a":0,"k":[0,0.388235300779,0.466666668653,1],"ix":3},"o":{"a":0,"k":100,"ix":4},"w":{"a":0,"k":1.897,"ix":5},"lc":1,"lj":1,"ml":10,"bm":0,"nm":"Stroke 1","mn":"ADBE Vector Graphic - Stroke","hd":false},{"ty":"fl","c":{"a":0,"k":[1,1,1,1],"ix":4},"o":{"a":0,"k":100,"ix":5},"r":1,"bm":0,"nm":"Fill 1","mn":"ADBE Vector Graphic - Fill","hd":false},{"ty":"tr","p":{"a":0,"k":[0,0],"ix":2},"a":{"a":0,"k":[0,0],"ix":1},"s":{"a":0,"k":[100,100],"ix":3},"r":{"a":0,"k":0,"ix":6},"o":{"a":0,"k":100,"ix":7},"sk":{"a":0,"k":0,"ix":4},"sa":{"a":0,"k":0,"ix":5},"nm":"Transform"}],"nm":"Lokaal geproduceerd","np":3,"cix":2,"bm":0,"ix":1,"mn":"ADBE Vector Group","hd":false}],"ip":0,"op":96,"st":0,"ct":1,"bm":0},{"ddd":0,"ind":10,"ty":4,"nm":"Tulp Mid 2","parent":1,"sr":1,"ks":{"o":{"a":1,"k":[{"i":{"x":[0.833],"y":[0.833]},"o":{"x":[0.167],"y":[0.167]},"t":61,"s":[100]},{"i":{"x":[0.833],"y":[0.833]},"o":{"x":[0.167],"y":[0.167]},"t":62,"s":[0]},{"i":{"x":[0.833],"y":[0.833]},"o":{"x":[0.167],"y":[0.167]},"t":78,"s":[0]},{"t":79,"s":[100]}],"ix":11},"r":{"a":0,"k":15,"ix":10},"p":{"a":0,"k":[19.5,-70.5,0],"ix":2,"l":2},"a":{"a":0,"k":[0,0,0],"ix":1,"l":2},"s":{"a":0,"k":[200,200,100],"ix":6,"l":2}},"ao":0,"shapes":[{"ty":"gr","it":[{"ind":0,"ty":"sh","ix":1,"ks":{"a":0,"k":{"i":[[0,0],[0,0],[-1.664,-15.729],[-14.696,0],[0,0],[-0.44,13.345]],"o":[[0,0],[0,0],[1.664,15.729],[0,0],[14.696,0],[0.44,-13.345]],"v":[[0.215,-37.54],[0.089,-37.402],[-26.61,9.979],[0,36.589],[0,36.589],[26.61,9.979]],"c":true},"ix":2},"nm":"Path 1","mn":"ADBE Vector Shape - Group","hd":false},{"ty":"st","c":{"a":0,"k":[0,0.388235300779,0.466666668653,1],"ix":3},"o":{"a":0,"k":100,"ix":4},"w":{"a":0,"k":1.897,"ix":5},"lc":1,"lj":1,"ml":10,"bm":0,"d":[{"n":"d","nm":"dash","v":{"a":0,"k":10,"ix":1}},{"n":"g","nm":"gap","v":{"a":0,"k":10,"ix":2}},{"n":"o","nm":"offset","v":{"a":0,"k":0,"ix":7}}],"nm":"Stroke 1","mn":"ADBE Vector Graphic - Stroke","hd":false},{"ty":"tr","p":{"a":0,"k":[0,0],"ix":2},"a":{"a":0,"k":[0,0],"ix":1},"s":{"a":0,"k":[100,100],"ix":3},"r":{"a":0,"k":0,"ix":6},"o":{"a":0,"k":100,"ix":7},"sk":{"a":0,"k":0,"ix":4},"sa":{"a":0,"k":0,"ix":5},"nm":"Transform"}],"nm":"Lokaal geproduceerd","np":3,"cix":2,"bm":0,"ix":1,"mn":"ADBE Vector Group","hd":false}],"ip":0,"op":96,"st":0,"ct":1,"bm":0},{"ddd":0,"ind":11,"ty":4,"nm":"Tulp Mid 3","parent":1,"sr":1,"ks":{"o":{"a":1,"k":[{"i":{"x":[0.833],"y":[0.833]},"o":{"x":[0.167],"y":[0.167]},"t":61,"s":[100]},{"i":{"x":[0.833],"y":[0.833]},"o":{"x":[0.167],"y":[0.167]},"t":62,"s":[0]},{"i":{"x":[0.833],"y":[0.833]},"o":{"x":[0.167],"y":[0.167]},"t":78,"s":[0]},{"t":79,"s":[100]}],"ix":11},"r":{"a":0,"k":15,"ix":10},"p":{"a":0,"k":[19.5,-70.5,0],"ix":2,"l":2},"a":{"a":0,"k":[0,0,0],"ix":1,"l":2},"s":{"a":0,"k":[200,200,100],"ix":6,"l":2}},"ao":0,"shapes":[{"ty":"gr","it":[{"ind":0,"ty":"sh","ix":1,"ks":{"a":0,"k":{"i":[[0,0],[0,0],[-1.664,-15.729],[-14.696,0],[0,0],[-0.44,13.345]],"o":[[0,0],[0,0],[1.664,15.729],[0,0],[14.696,0],[0.44,-13.345]],"v":[[0.215,-37.54],[0.089,-37.402],[-26.61,9.979],[0,36.589],[0,36.589],[26.61,9.979]],"c":true},"ix":2},"nm":"Path 1","mn":"ADBE Vector Shape - Group","hd":false},{"ty":"st","c":{"a":0,"k":[0,0.388235300779,0.466666668653,1],"ix":3},"o":{"a":0,"k":100,"ix":4},"w":{"a":0,"k":1.897,"ix":5},"lc":1,"lj":1,"ml":10,"bm":0,"d":[{"n":"d","nm":"dash","v":{"a":0,"k":10,"ix":1}},{"n":"g","nm":"gap","v":{"a":0,"k":10,"ix":2}},{"n":"o","nm":"offset","v":{"a":0,"k":0,"ix":7}}],"nm":"Stroke 1","mn":"ADBE Vector Graphic - Stroke","hd":false},{"ty":"fl","c":{"a":0,"k":[1,1,1,1],"ix":4},"o":{"a":0,"k":100,"ix":5},"r":1,"bm":0,"nm":"Fill 1","mn":"ADBE Vector Graphic - Fill","hd":false},{"ty":"tr","p":{"a":0,"k":[0,0],"ix":2},"a":{"a":0,"k":[0,0],"ix":1},"s":{"a":0,"k":[100,100],"ix":3},"r":{"a":0,"k":0,"ix":6},"o":{"a":0,"k":100,"ix":7},"sk":{"a":0,"k":0,"ix":4},"sa":{"a":0,"k":0,"ix":5},"nm":"Transform"}],"nm":"Lokaal geproduceerd","np":3,"cix":2,"bm":0,"ix":1,"mn":"ADBE Vector Group","hd":false}],"ip":0,"op":96,"st":0,"ct":1,"bm":0},{"ddd":0,"ind":12,"ty":4,"nm":"Tulp Mid","parent":1,"sr":1,"ks":{"o":{"a":0,"k":100,"ix":11},"r":{"a":0,"k":15,"ix":10},"p":{"a":0,"k":[19.5,-70.5,0],"ix":2,"l":2},"a":{"a":0,"k":[0,0,0],"ix":1,"l":2},"s":{"a":0,"k":[200,200,100],"ix":6,"l":2}},"ao":0,"shapes":[{"ty":"gr","it":[{"ind":0,"ty":"sh","ix":1,"ks":{"a":1,"k":[{"i":{"x":0.2,"y":1},"o":{"x":0.6,"y":0.1},"t":54,"s":[{"i":[[0,0],[0,0],[0,0],[-14.696,0],[0,0],[0,14.696]],"o":[[0,0],[0,0],[0,14.696],[0,0],[14.696,0],[0,0]],"v":[[26.61,-36.589],[-26.61,-36.589],[-26.61,9.979],[0,36.589],[0,36.589],[26.61,9.979]],"c":true}]},{"i":{"x":0.833,"y":1},"o":{"x":0.167,"y":0},"t":66,"s":[{"i":[[0,0],[0,0],[-1.664,-15.729],[-14.696,0],[0,0],[-0.44,13.345]],"o":[[0,0],[0,0],[1.664,15.729],[0,0],[14.696,0],[0.44,-13.345]],"v":[[0.215,-37.54],[0.089,-37.402],[-26.61,9.979],[0,36.589],[0,36.589],[26.61,9.979]],"c":true}]},{"i":{"x":0.6,"y":1},"o":{"x":0.32,"y":0.94},"t":78,"s":[{"i":[[0,0],[0,0],[-1.664,-15.729],[-14.696,0],[0,0],[-0.44,13.345]],"o":[[0,0],[0,0],[1.664,15.729],[0,0],[14.696,0],[0.44,-13.345]],"v":[[0.215,-37.54],[0.089,-37.402],[-26.61,9.979],[0,36.589],[0,36.589],[26.61,9.979]],"c":true}]},{"t":84,"s":[{"i":[[0,0],[0,0],[0,0],[-14.696,0],[0,0],[0,14.696]],"o":[[0,0],[0,0],[0,14.696],[0,0],[14.696,0],[0,0]],"v":[[26.61,-36.589],[-26.61,-36.589],[-26.61,9.979],[0,36.589],[0,36.589],[26.61,9.979]],"c":true}]}],"ix":2},"nm":"Path 1","mn":"ADBE Vector Shape - Group","hd":false},{"ty":"st","c":{"a":0,"k":[0,0.388235300779,0.466666668653,1],"ix":3},"o":{"a":0,"k":100,"ix":4},"w":{"a":0,"k":1.897,"ix":5},"lc":1,"lj":1,"ml":10,"bm":0,"nm":"Stroke 1","mn":"ADBE Vector Graphic - Stroke","hd":false},{"ty":"tr","p":{"a":0,"k":[0,0],"ix":2},"a":{"a":0,"k":[0,0],"ix":1},"s":{"a":0,"k":[100,100],"ix":3},"r":{"a":0,"k":0,"ix":6},"o":{"a":0,"k":100,"ix":7},"sk":{"a":0,"k":0,"ix":4},"sa":{"a":0,"k":0,"ix":5},"nm":"Transform"}],"nm":"Lokaal geproduceerd","np":3,"cix":2,"bm":0,"ix":1,"mn":"ADBE Vector Group","hd":false}],"ip":0,"op":96,"st":0,"ct":1,"bm":0},{"ddd":0,"ind":13,"ty":4,"nm":"Tulp Mid 4","parent":1,"sr":1,"ks":{"o":{"a":0,"k":100,"ix":11},"r":{"a":0,"k":15,"ix":10},"p":{"a":0,"k":[19.5,-70.5,0],"ix":2,"l":2},"a":{"a":0,"k":[0,0,0],"ix":1,"l":2},"s":{"a":0,"k":[200,200,100],"ix":6,"l":2}},"ao":0,"shapes":[{"ty":"gr","it":[{"ind":0,"ty":"sh","ix":1,"ks":{"a":1,"k":[{"i":{"x":0.2,"y":1},"o":{"x":0.6,"y":0.1},"t":54,"s":[{"i":[[0,0],[0,0],[0,0],[-14.696,0],[0,0],[0,14.696]],"o":[[0,0],[0,0],[0,14.696],[0,0],[14.696,0],[0,0]],"v":[[26.61,-36.589],[-26.61,-36.589],[-26.61,9.979],[0,36.589],[0,36.589],[26.61,9.979]],"c":true}]},{"i":{"x":0.833,"y":1},"o":{"x":0.167,"y":0},"t":66,"s":[{"i":[[0,0],[0,0],[-1.664,-15.729],[-14.696,0],[0,0],[-0.44,13.345]],"o":[[0,0],[0,0],[1.664,15.729],[0,0],[14.696,0],[0.44,-13.345]],"v":[[0.215,-37.54],[0.089,-37.402],[-26.61,9.979],[0,36.589],[0,36.589],[26.61,9.979]],"c":true}]},{"i":{"x":0.6,"y":1},"o":{"x":0.32,"y":0.94},"t":78,"s":[{"i":[[0,0],[0,0],[-1.664,-15.729],[-14.696,0],[0,0],[-0.44,13.345]],"o":[[0,0],[0,0],[1.664,15.729],[0,0],[14.696,0],[0.44,-13.345]],"v":[[0.215,-37.54],[0.089,-37.402],[-26.61,9.979],[0,36.589],[0,36.589],[26.61,9.979]],"c":true}]},{"t":84,"s":[{"i":[[0,0],[0,0],[0,0],[-14.696,0],[0,0],[0,14.696]],"o":[[0,0],[0,0],[0,14.696],[0,0],[14.696,0],[0,0]],"v":[[26.61,-36.589],[-26.61,-36.589],[-26.61,9.979],[0,36.589],[0,36.589],[26.61,9.979]],"c":true}]}],"ix":2},"nm":"Path 1","mn":"ADBE Vector Shape - Group","hd":false},{"ty":"st","c":{"a":0,"k":[0,0.388235300779,0.466666668653,1],"ix":3},"o":{"a":0,"k":100,"ix":4},"w":{"a":0,"k":1.897,"ix":5},"lc":1,"lj":1,"ml":10,"bm":0,"nm":"Stroke 1","mn":"ADBE Vector Graphic - Stroke","hd":false},{"ty":"fl","c":{"a":0,"k":[1,1,1,1],"ix":4},"o":{"a":0,"k":100,"ix":5},"r":1,"bm":0,"nm":"Fill 1","mn":"ADBE Vector Graphic - Fill","hd":false},{"ty":"tr","p":{"a":0,"k":[0,0],"ix":2},"a":{"a":0,"k":[0,0],"ix":1},"s":{"a":0,"k":[100,100],"ix":3},"r":{"a":0,"k":0,"ix":6},"o":{"a":0,"k":100,"ix":7},"sk":{"a":0,"k":0,"ix":4},"sa":{"a":0,"k":0,"ix":5},"nm":"Transform"}],"nm":"Lokaal geproduceerd","np":3,"cix":2,"bm":0,"ix":1,"mn":"ADBE Vector Group","hd":false}],"ip":0,"op":96,"st":0,"ct":1,"bm":0},{"ddd":0,"ind":16,"ty":4,"nm":"Blad onder","parent":18,"sr":1,"ks":{"o":{"a":0,"k":100,"ix":11},"r":{"a":1,"k":[{"i":{"x":[0.91],"y":[1]},"o":{"x":[0.751],"y":[0]},"t":0,"s":[-15]},{"i":{"x":[0.667],"y":[1]},"o":{"x":[0.66],"y":[0]},"t":78,"s":[-18]},{"i":{"x":[0.833],"y":[1]},"o":{"x":[0.333],"y":[0]},"t":84,"s":[-13]},{"t":95,"s":[-15]}],"ix":10},"p":{"a":0,"k":[-1.452,50.524,0],"ix":2,"l":2},"a":{"a":0,"k":[-40.689,39.44,0],"ix":1,"l":2},"s":{"a":0,"k":[100,100,100],"ix":6,"l":2}},"ao":0,"ef":[{"ty":5,"nm":"CC Bend It","np":7,"mn":"CC Bend It","ix":1,"en":1,"ef":[{"ty":0,"nm":"Bend","mn":"CC Bend It-0001","ix":1,"v":{"a":1,"k":[{"i":{"x":[0.667],"y":[1]},"o":{"x":[0.333],"y":[0]},"t":0,"s":[0]},{"i":{"x":[0.667],"y":[1]},"o":{"x":[0.333],"y":[0]},"t":72,"s":[4]},{"i":{"x":[0.667],"y":[1]},"o":{"x":[0.333],"y":[0]},"t":80,"s":[-4]},{"i":{"x":[0.667],"y":[1]},"o":{"x":[0.333],"y":[0]},"t":86,"s":[7]},{"t":95,"s":[0]}],"ix":1}},{"ty":3,"nm":"Start","mn":"CC Bend It-0002","ix":2,"v":{"k":[{"s":[175.889,420.603],"t":55,"i":{"x":1,"y":1},"o":{"x":0,"y":0}},{"s":[175.718,420.698],"t":73,"i":{"x":1,"y":1},"o":{"x":0,"y":0}},{"s":[175.874,420.408],"t":81,"i":{"x":1,"y":1},"o":{"x":0,"y":0}},{"s":[176.054,420.4],"t":82,"i":{"x":1,"y":1},"o":{"x":0,"y":0}},{"s":[176.236,420.407],"t":83,"i":{"x":1,"y":1},"o":{"x":0,"y":0}}]}},{"ty":3,"nm":"End","mn":"CC Bend It-0003","ix":3,"v":{"k":[{"s":[369.359,155.707],"t":4,"i":{"x":1,"y":1},"o":{"x":0,"y":0}},{"s":[369.153,155.559],"t":6,"i":{"x":1,"y":1},"o":{"x":0,"y":0}},{"s":[369.024,155.468],"t":7,"i":{"x":1,"y":1},"o":{"x":0,"y":0}},{"s":[368.88,155.365],"t":8,"i":{"x":1,"y":1},"o":{"x":0,"y":0}},{"s":[368.72,155.252],"t":9,"i":{"x":1,"y":1},"o":{"x":0,"y":0}},{"s":[368.547,155.129],"t":10,"i":{"x":1,"y":1},"o":{"x":0,"y":0}},{"s":[368.359,154.996],"t":11,"i":{"x":1,"y":1},"o":{"x":0,"y":0}},{"s":[368.159,154.854],"t":12,"i":{"x":1,"y":1},"o":{"x":0,"y":0}},{"s":[367.945,154.704],"t":13,"i":{"x":1,"y":1},"o":{"x":0,"y":0}},{"s":[367.719,154.545],"t":14,"i":{"x":1,"y":1},"o":{"x":0,"y":0}},{"s":[367.481,154.377],"t":15,"i":{"x":1,"y":1},"o":{"x":0,"y":0}},{"s":[367.232,154.202],"t":16,"i":{"x":1,"y":1},"o":{"x":0,"y":0}},{"s":[366.971,154.02],"t":17,"i":{"x":1,"y":1},"o":{"x":0,"y":0}},{"s":[366.699,153.829],"t":18,"i":{"x":1,"y":1},"o":{"x":0,"y":0}},{"s":[366.416,153.632],"t":19,"i":{"x":1,"y":1},"o":{"x":0,"y":0}},{"s":[366.123,153.428],"t":20,"i":{"x":1,"y":1},"o":{"x":0,"y":0}},{"s":[365.819,153.217],"t":21,"i":{"x":1,"y":1},"o":{"x":0,"y":0}},{"s":[365.505,153],"t":22,"i":{"x":1,"y":1},"o":{"x":0,"y":0}},{"s":[365.181,152.776],"t":23,"i":{"x":1,"y":1},"o":{"x":0,"y":0}},{"s":[364.847,152.546],"t":24,"i":{"x":1,"y":1},"o":{"x":0,"y":0}},{"s":[364.503,152.31],"t":25,"i":{"x":1,"y":1},"o":{"x":0,"y":0}},{"s":[364.149,152.067],"t":26,"i":{"x":1,"y":1},"o":{"x":0,"y":0}},{"s":[363.786,151.819],"t":27,"i":{"x":1,"y":1},"o":{"x":0,"y":0}},{"s":[363.413,151.565],"t":28,"i":{"x":1,"y":1},"o":{"x":0,"y":0}},{"s":[363.031,151.306],"t":29,"i":{"x":1,"y":1},"o":{"x":0,"y":0}},{"s":[362.639,151.04],"t":30,"i":{"x":1,"y":1},"o":{"x":0,"y":0}},{"s":[362.238,150.77],"t":31,"i":{"x":1,"y":1},"o":{"x":0,"y":0}},{"s":[361.827,150.493],"t":32,"i":{"x":1,"y":1},"o":{"x":0,"y":0}},{"s":[361.407,150.212],"t":33,"i":{"x":1,"y":1},"o":{"x":0,"y":0}},{"s":[360.978,149.925],"t":34,"i":{"x":1,"y":1},"o":{"x":0,"y":0}},{"s":[360.539,149.633],"t":35,"i":{"x":1,"y":1},"o":{"x":0,"y":0}},{"s":[360.091,149.335],"t":36,"i":{"x":1,"y":1},"o":{"x":0,"y":0}},{"s":[359.634,149.033],"t":37,"i":{"x":1,"y":1},"o":{"x":0,"y":0}},{"s":[359.167,148.725],"t":38,"i":{"x":1,"y":1},"o":{"x":0,"y":0}},{"s":[358.69,148.412],"t":39,"i":{"x":1,"y":1},"o":{"x":0,"y":0}},{"s":[358.204,148.095],"t":40,"i":{"x":1,"y":1},"o":{"x":0,"y":0}},{"s":[357.708,147.772],"t":41,"i":{"x":1,"y":1},"o":{"x":0,"y":0}},{"s":[357.203,147.444],"t":42,"i":{"x":1,"y":1},"o":{"x":0,"y":0}},{"s":[356.688,147.111],"t":43,"i":{"x":1,"y":1},"o":{"x":0,"y":0}},{"s":[356.163,146.773],"t":44,"i":{"x":1,"y":1},"o":{"x":0,"y":0}},{"s":[355.628,146.431],"t":45,"i":{"x":1,"y":1},"o":{"x":0,"y":0}},{"s":[355.083,146.083],"t":46,"i":{"x":1,"y":1},"o":{"x":0,"y":0}},{"s":[354.528,145.731],"t":47,"i":{"x":1,"y":1},"o":{"x":0,"y":0}},{"s":[353.963,145.373],"t":48,"i":{"x":1,"y":1},"o":{"x":0,"y":0}},{"s":[353.387,145.011],"t":49,"i":{"x":1,"y":1},"o":{"x":0,"y":0}},{"s":[352.801,144.644],"t":50,"i":{"x":1,"y":1},"o":{"x":0,"y":0}},{"s":[352.204,144.272],"t":51,"i":{"x":1,"y":1},"o":{"x":0,"y":0}},{"s":[351.597,143.895],"t":52,"i":{"x":1,"y":1},"o":{"x":0,"y":0}},{"s":[350.978,143.513],"t":53,"i":{"x":1,"y":1},"o":{"x":0,"y":0}},{"s":[350.349,143.126],"t":54,"i":{"x":1,"y":1},"o":{"x":0,"y":0}},{"s":[349.709,142.735],"t":55,"i":{"x":1,"y":1},"o":{"x":0,"y":0}},{"s":[349.057,142.339],"t":56,"i":{"x":1,"y":1},"o":{"x":0,"y":0}},{"s":[348.394,141.938],"t":57,"i":{"x":1,"y":1},"o":{"x":0,"y":0}},{"s":[347.72,141.532],"t":58,"i":{"x":1,"y":1},"o":{"x":0,"y":0}},{"s":[347.035,141.122],"t":59,"i":{"x":1,"y":1},"o":{"x":0,"y":0}},{"s":[346.339,140.708],"t":60,"i":{"x":1,"y":1},"o":{"x":0,"y":0}},{"s":[345.631,140.289],"t":61,"i":{"x":1,"y":1},"o":{"x":0,"y":0}},{"s":[344.913,139.866],"t":62,"i":{"x":1,"y":1},"o":{"x":0,"y":0}},{"s":[344.185,139.44],"t":63,"i":{"x":1,"y":1},"o":{"x":0,"y":0}},{"s":[343.447,139.011],"t":64,"i":{"x":1,"y":1},"o":{"x":0,"y":0}},{"s":[342.701,138.58],"t":65,"i":{"x":1,"y":1},"o":{"x":0,"y":0}},{"s":[341.947,138.147],"t":66,"i":{"x":1,"y":1},"o":{"x":0,"y":0}},{"s":[341.19,137.715],"t":67,"i":{"x":1,"y":1},"o":{"x":0,"y":0}},{"s":[340.431,137.284],"t":68,"i":{"x":1,"y":1},"o":{"x":0,"y":0}},{"s":[339.675,136.858],"t":69,"i":{"x":1,"y":1},"o":{"x":0,"y":0}},{"s":[338.931,136.441],"t":70,"i":{"x":1,"y":1},"o":{"x":0,"y":0}},{"s":[338.213,136.04],"t":71,"i":{"x":1,"y":1},"o":{"x":0,"y":0}},{"s":[337.543,135.669],"t":72,"i":{"x":1,"y":1},"o":{"x":0,"y":0}},{"s":[336.986,135.362],"t":73,"i":{"x":1,"y":1},"o":{"x":0,"y":0}},{"s":[336.795,135.255],"t":75,"i":{"x":1,"y":1},"o":{"x":0,"y":0}},{"s":[337.519,135.652],"t":76,"i":{"x":1,"y":1},"o":{"x":0,"y":0}},{"s":[339.281,136.63],"t":77,"i":{"x":1,"y":1},"o":{"x":0,"y":0}},{"s":[342.848,138.655],"t":78,"i":{"x":1,"y":1},"o":{"x":0,"y":0}},{"s":[348.487,141.979],"t":79,"i":{"x":1,"y":1},"o":{"x":0,"y":0}},{"s":[354.192,145.506],"t":80,"i":{"x":1,"y":1},"o":{"x":0,"y":0}},{"s":[360.485,149.589],"t":81,"i":{"x":1,"y":1},"o":{"x":0,"y":0}},{"s":[368.712,155.246],"t":82,"i":{"x":1,"y":1},"o":{"x":0,"y":0}},{"s":[376.413,160.882],"t":83,"i":{"x":1,"y":1},"o":{"x":0,"y":0}},{"s":[378.89,162.768],"t":84,"i":{"x":1,"y":1},"o":{"x":0,"y":0}},{"s":[378.69,162.614],"t":85,"i":{"x":1,"y":1},"o":{"x":0,"y":0}},{"s":[378.181,162.224],"t":86,"i":{"x":1,"y":1},"o":{"x":0,"y":0}},{"s":[377.451,161.668],"t":87,"i":{"x":1,"y":1},"o":{"x":0,"y":0}},{"s":[376.56,160.993],"t":88,"i":{"x":1,"y":1},"o":{"x":0,"y":0}},{"s":[375.55,160.233],"t":89,"i":{"x":1,"y":1},"o":{"x":0,"y":0}},{"s":[374.456,159.417],"t":90,"i":{"x":1,"y":1},"o":{"x":0,"y":0}},{"s":[373.312,158.571],"t":91,"i":{"x":1,"y":1},"o":{"x":0,"y":0}},{"s":[372.156,157.724],"t":92,"i":{"x":1,"y":1},"o":{"x":0,"y":0}},{"s":[371.041,156.914],"t":93,"i":{"x":1,"y":1},"o":{"x":0,"y":0}},{"s":[370.068,156.213],"t":94,"i":{"x":1,"y":1},"o":{"x":0,"y":0}},{"s":[369.539,155.834],"t":95,"i":{"x":1,"y":1},"o":{"x":0,"y":0}}]}},{"ty":7,"nm":"Render Prestart","mn":"CC Bend It-0004","ix":4,"v":{"a":0,"k":3,"ix":4}},{"ty":7,"nm":"Distort","mn":"CC Bend It-0005","ix":5,"v":{"a":0,"k":1,"ix":5}}]}],"shapes":[{"ty":"gr","it":[{"ind":0,"ty":"sh","ix":1,"ks":{"a":0,"k":{"i":[[0,0],[0,0],[14.029,3.759],[0,0],[0,0],[-6.102,4.077]],"o":[[0,0],[-7.262,12.578],[0,0],[0,0],[2.185,-7.005],[0,0]],"v":[[40.689,-39.44],[4.413,23.392],[-31.684,38.344],[-40.689,35.931],[-35.792,20.23],[-22.985,3.103]],"c":true},"ix":2},"nm":"Path 1","mn":"ADBE Vector Shape - Group","hd":false},{"ty":"st","c":{"a":0,"k":[0,0.388235300779,0.466666668653,1],"ix":3},"o":{"a":0,"k":100,"ix":4},"w":{"a":0,"k":1.897,"ix":5},"lc":1,"lj":1,"ml":10,"bm":0,"nm":"Stroke 1","mn":"ADBE Vector Graphic - Stroke","hd":false},{"ty":"tr","p":{"a":0,"k":[0,0],"ix":2},"a":{"a":0,"k":[0,0],"ix":1},"s":{"a":0,"k":[100,100],"ix":3},"r":{"a":0,"k":0,"ix":6},"o":{"a":0,"k":100,"ix":7},"sk":{"a":0,"k":0,"ix":4},"sa":{"a":0,"k":0,"ix":5},"nm":"Transform"}],"nm":"Blad onder","np":3,"cix":2,"bm":0,"ix":1,"mn":"ADBE Vector Group","hd":false}],"ip":0,"op":96,"st":0,"ct":1,"bm":0},{"ddd":0,"ind":17,"ty":4,"nm":"Blad onder 2","parent":18,"sr":1,"ks":{"o":{"a":0,"k":100,"ix":11},"r":{"a":1,"k":[{"i":{"x":[0.91],"y":[1]},"o":{"x":[0.751],"y":[0]},"t":0,"s":[-15]},{"i":{"x":[0.667],"y":[1]},"o":{"x":[0.66],"y":[0]},"t":78,"s":[-18]},{"i":{"x":[0.833],"y":[1]},"o":{"x":[0.333],"y":[0]},"t":84,"s":[-13]},{"t":95,"s":[-15]}],"ix":10},"p":{"a":0,"k":[-1.452,50.524,0],"ix":2,"l":2},"a":{"a":0,"k":[-40.689,39.44,0],"ix":1,"l":2},"s":{"a":0,"k":[100,100,100],"ix":6,"l":2}},"ao":0,"ef":[{"ty":5,"nm":"CC Bend It","np":7,"mn":"CC Bend It","ix":1,"en":1,"ef":[{"ty":0,"nm":"Bend","mn":"CC Bend It-0001","ix":1,"v":{"a":1,"k":[{"i":{"x":[0.667],"y":[1]},"o":{"x":[0.333],"y":[0]},"t":0,"s":[0]},{"i":{"x":[0.667],"y":[1]},"o":{"x":[0.333],"y":[0]},"t":72,"s":[4]},{"i":{"x":[0.667],"y":[1]},"o":{"x":[0.333],"y":[0]},"t":80,"s":[-4]},{"i":{"x":[0.667],"y":[1]},"o":{"x":[0.333],"y":[0]},"t":86,"s":[7]},{"t":95,"s":[0]}],"ix":1}},{"ty":3,"nm":"Start","mn":"CC Bend It-0002","ix":2,"v":{"k":[{"s":[175.889,420.603],"t":55,"i":{"x":1,"y":1},"o":{"x":0,"y":0}},{"s":[175.718,420.698],"t":73,"i":{"x":1,"y":1},"o":{"x":0,"y":0}},{"s":[175.874,420.408],"t":81,"i":{"x":1,"y":1},"o":{"x":0,"y":0}},{"s":[176.054,420.4],"t":82,"i":{"x":1,"y":1},"o":{"x":0,"y":0}},{"s":[176.236,420.407],"t":83,"i":{"x":1,"y":1},"o":{"x":0,"y":0}}]}},{"ty":3,"nm":"End","mn":"CC Bend It-0003","ix":3,"v":{"k":[{"s":[369.359,155.707],"t":4,"i":{"x":1,"y":1},"o":{"x":0,"y":0}},{"s":[369.153,155.559],"t":6,"i":{"x":1,"y":1},"o":{"x":0,"y":0}},{"s":[369.024,155.468],"t":7,"i":{"x":1,"y":1},"o":{"x":0,"y":0}},{"s":[368.88,155.365],"t":8,"i":{"x":1,"y":1},"o":{"x":0,"y":0}},{"s":[368.72,155.252],"t":9,"i":{"x":1,"y":1},"o":{"x":0,"y":0}},{"s":[368.547,155.129],"t":10,"i":{"x":1,"y":1},"o":{"x":0,"y":0}},{"s":[368.359,154.996],"t":11,"i":{"x":1,"y":1},"o":{"x":0,"y":0}},{"s":[368.159,154.854],"t":12,"i":{"x":1,"y":1},"o":{"x":0,"y":0}},{"s":[367.945,154.704],"t":13,"i":{"x":1,"y":1},"o":{"x":0,"y":0}},{"s":[367.719,154.545],"t":14,"i":{"x":1,"y":1},"o":{"x":0,"y":0}},{"s":[367.481,154.377],"t":15,"i":{"x":1,"y":1},"o":{"x":0,"y":0}},{"s":[367.232,154.202],"t":16,"i":{"x":1,"y":1},"o":{"x":0,"y":0}},{"s":[366.971,154.02],"t":17,"i":{"x":1,"y":1},"o":{"x":0,"y":0}},{"s":[366.699,153.829],"t":18,"i":{"x":1,"y":1},"o":{"x":0,"y":0}},{"s":[366.416,153.632],"t":19,"i":{"x":1,"y":1},"o":{"x":0,"y":0}},{"s":[366.123,153.428],"t":20,"i":{"x":1,"y":1},"o":{"x":0,"y":0}},{"s":[365.819,153.217],"t":21,"i":{"x":1,"y":1},"o":{"x":0,"y":0}},{"s":[365.505,153],"t":22,"i":{"x":1,"y":1},"o":{"x":0,"y":0}},{"s":[365.181,152.776],"t":23,"i":{"x":1,"y":1},"o":{"x":0,"y":0}},{"s":[364.847,152.546],"t":24,"i":{"x":1,"y":1},"o":{"x":0,"y":0}},{"s":[364.503,152.31],"t":25,"i":{"x":1,"y":1},"o":{"x":0,"y":0}},{"s":[364.149,152.067],"t":26,"i":{"x":1,"y":1},"o":{"x":0,"y":0}},{"s":[363.786,151.819],"t":27,"i":{"x":1,"y":1},"o":{"x":0,"y":0}},{"s":[363.413,151.565],"t":28,"i":{"x":1,"y":1},"o":{"x":0,"y":0}},{"s":[363.031,151.306],"t":29,"i":{"x":1,"y":1},"o":{"x":0,"y":0}},{"s":[362.639,151.04],"t":30,"i":{"x":1,"y":1},"o":{"x":0,"y":0}},{"s":[362.238,150.77],"t":31,"i":{"x":1,"y":1},"o":{"x":0,"y":0}},{"s":[361.827,150.493],"t":32,"i":{"x":1,"y":1},"o":{"x":0,"y":0}},{"s":[361.407,150.212],"t":33,"i":{"x":1,"y":1},"o":{"x":0,"y":0}},{"s":[360.978,149.925],"t":34,"i":{"x":1,"y":1},"o":{"x":0,"y":0}},{"s":[360.539,149.633],"t":35,"i":{"x":1,"y":1},"o":{"x":0,"y":0}},{"s":[360.091,149.335],"t":36,"i":{"x":1,"y":1},"o":{"x":0,"y":0}},{"s":[359.634,149.033],"t":37,"i":{"x":1,"y":1},"o":{"x":0,"y":0}},{"s":[359.167,148.725],"t":38,"i":{"x":1,"y":1},"o":{"x":0,"y":0}},{"s":[358.69,148.412],"t":39,"i":{"x":1,"y":1},"o":{"x":0,"y":0}},{"s":[358.204,148.095],"t":40,"i":{"x":1,"y":1},"o":{"x":0,"y":0}},{"s":[357.708,147.772],"t":41,"i":{"x":1,"y":1},"o":{"x":0,"y":0}},{"s":[357.203,147.444],"t":42,"i":{"x":1,"y":1},"o":{"x":0,"y":0}},{"s":[356.688,147.111],"t":43,"i":{"x":1,"y":1},"o":{"x":0,"y":0}},{"s":[356.163,146.773],"t":44,"i":{"x":1,"y":1},"o":{"x":0,"y":0}},{"s":[355.628,146.431],"t":45,"i":{"x":1,"y":1},"o":{"x":0,"y":0}},{"s":[355.083,146.083],"t":46,"i":{"x":1,"y":1},"o":{"x":0,"y":0}},{"s":[354.528,145.731],"t":47,"i":{"x":1,"y":1},"o":{"x":0,"y":0}},{"s":[353.963,145.373],"t":48,"i":{"x":1,"y":1},"o":{"x":0,"y":0}},{"s":[353.387,145.011],"t":49,"i":{"x":1,"y":1},"o":{"x":0,"y":0}},{"s":[352.801,144.644],"t":50,"i":{"x":1,"y":1},"o":{"x":0,"y":0}},{"s":[352.204,144.272],"t":51,"i":{"x":1,"y":1},"o":{"x":0,"y":0}},{"s":[351.597,143.895],"t":52,"i":{"x":1,"y":1},"o":{"x":0,"y":0}},{"s":[350.978,143.513],"t":53,"i":{"x":1,"y":1},"o":{"x":0,"y":0}},{"s":[350.349,143.126],"t":54,"i":{"x":1,"y":1},"o":{"x":0,"y":0}},{"s":[349.709,142.735],"t":55,"i":{"x":1,"y":1},"o":{"x":0,"y":0}},{"s":[349.057,142.339],"t":56,"i":{"x":1,"y":1},"o":{"x":0,"y":0}},{"s":[348.394,141.938],"t":57,"i":{"x":1,"y":1},"o":{"x":0,"y":0}},{"s":[347.72,141.532],"t":58,"i":{"x":1,"y":1},"o":{"x":0,"y":0}},{"s":[347.035,141.122],"t":59,"i":{"x":1,"y":1},"o":{"x":0,"y":0}},{"s":[346.339,140.708],"t":60,"i":{"x":1,"y":1},"o":{"x":0,"y":0}},{"s":[345.631,140.289],"t":61,"i":{"x":1,"y":1},"o":{"x":0,"y":0}},{"s":[344.913,139.866],"t":62,"i":{"x":1,"y":1},"o":{"x":0,"y":0}},{"s":[344.185,139.44],"t":63,"i":{"x":1,"y":1},"o":{"x":0,"y":0}},{"s":[343.447,139.011],"t":64,"i":{"x":1,"y":1},"o":{"x":0,"y":0}},{"s":[342.701,138.58],"t":65,"i":{"x":1,"y":1},"o":{"x":0,"y":0}},{"s":[341.947,138.147],"t":66,"i":{"x":1,"y":1},"o":{"x":0,"y":0}},{"s":[341.19,137.715],"t":67,"i":{"x":1,"y":1},"o":{"x":0,"y":0}},{"s":[340.431,137.284],"t":68,"i":{"x":1,"y":1},"o":{"x":0,"y":0}},{"s":[339.675,136.858],"t":69,"i":{"x":1,"y":1},"o":{"x":0,"y":0}},{"s":[338.931,136.441],"t":70,"i":{"x":1,"y":1},"o":{"x":0,"y":0}},{"s":[338.213,136.04],"t":71,"i":{"x":1,"y":1},"o":{"x":0,"y":0}},{"s":[337.543,135.669],"t":72,"i":{"x":1,"y":1},"o":{"x":0,"y":0}},{"s":[336.986,135.362],"t":73,"i":{"x":1,"y":1},"o":{"x":0,"y":0}},{"s":[336.795,135.255],"t":75,"i":{"x":1,"y":1},"o":{"x":0,"y":0}},{"s":[337.519,135.652],"t":76,"i":{"x":1,"y":1},"o":{"x":0,"y":0}},{"s":[339.281,136.63],"t":77,"i":{"x":1,"y":1},"o":{"x":0,"y":0}},{"s":[342.848,138.655],"t":78,"i":{"x":1,"y":1},"o":{"x":0,"y":0}},{"s":[348.487,141.979],"t":79,"i":{"x":1,"y":1},"o":{"x":0,"y":0}},{"s":[354.192,145.506],"t":80,"i":{"x":1,"y":1},"o":{"x":0,"y":0}},{"s":[360.485,149.589],"t":81,"i":{"x":1,"y":1},"o":{"x":0,"y":0}},{"s":[368.712,155.246],"t":82,"i":{"x":1,"y":1},"o":{"x":0,"y":0}},{"s":[376.413,160.882],"t":83,"i":{"x":1,"y":1},"o":{"x":0,"y":0}},{"s":[378.89,162.768],"t":84,"i":{"x":1,"y":1},"o":{"x":0,"y":0}},{"s":[378.69,162.614],"t":85,"i":{"x":1,"y":1},"o":{"x":0,"y":0}},{"s":[378.181,162.224],"t":86,"i":{"x":1,"y":1},"o":{"x":0,"y":0}},{"s":[377.451,161.668],"t":87,"i":{"x":1,"y":1},"o":{"x":0,"y":0}},{"s":[376.56,160.993],"t":88,"i":{"x":1,"y":1},"o":{"x":0,"y":0}},{"s":[375.55,160.233],"t":89,"i":{"x":1,"y":1},"o":{"x":0,"y":0}},{"s":[374.456,159.417],"t":90,"i":{"x":1,"y":1},"o":{"x":0,"y":0}},{"s":[373.312,158.571],"t":91,"i":{"x":1,"y":1},"o":{"x":0,"y":0}},{"s":[372.156,157.724],"t":92,"i":{"x":1,"y":1},"o":{"x":0,"y":0}},{"s":[371.041,156.914],"t":93,"i":{"x":1,"y":1},"o":{"x":0,"y":0}},{"s":[370.068,156.213],"t":94,"i":{"x":1,"y":1},"o":{"x":0,"y":0}},{"s":[369.539,155.834],"t":95,"i":{"x":1,"y":1},"o":{"x":0,"y":0}}]}},{"ty":7,"nm":"Render Prestart","mn":"CC Bend It-0004","ix":4,"v":{"a":0,"k":3,"ix":4}},{"ty":7,"nm":"Distort","mn":"CC Bend It-0005","ix":5,"v":{"a":0,"k":1,"ix":5}}]}],"shapes":[{"ty":"gr","it":[{"ind":0,"ty":"sh","ix":1,"ks":{"a":0,"k":{"i":[[0,0],[0,0],[14.029,3.759],[0,0],[0,0],[-6.102,4.077]],"o":[[0,0],[-7.262,12.578],[0,0],[0,0],[2.185,-7.005],[0,0]],"v":[[40.689,-39.44],[4.413,23.392],[-31.684,38.344],[-40.689,35.931],[-35.792,20.23],[-22.985,3.103]],"c":true},"ix":2},"nm":"Path 1","mn":"ADBE Vector Shape - Group","hd":false},{"ty":"st","c":{"a":0,"k":[0,0.388235300779,0.466666668653,1],"ix":3},"o":{"a":0,"k":100,"ix":4},"w":{"a":0,"k":1.897,"ix":5},"lc":1,"lj":1,"ml":10,"bm":0,"nm":"Stroke 1","mn":"ADBE Vector Graphic - Stroke","hd":false},{"ty":"fl","c":{"a":0,"k":[1,1,1,1],"ix":4},"o":{"a":0,"k":100,"ix":5},"r":1,"bm":0,"nm":"Fill 1","mn":"ADBE Vector Graphic - Fill","hd":false},{"ty":"tr","p":{"a":0,"k":[0,0],"ix":2},"a":{"a":0,"k":[0,0],"ix":1},"s":{"a":0,"k":[100,100],"ix":3},"r":{"a":0,"k":0,"ix":6},"o":{"a":0,"k":100,"ix":7},"sk":{"a":0,"k":0,"ix":4},"sa":{"a":0,"k":0,"ix":5},"nm":"Transform"}],"nm":"Blad onder","np":3,"cix":2,"bm":0,"ix":1,"mn":"ADBE Vector Group","hd":false}],"ip":0,"op":96,"st":0,"ct":1,"bm":0},{"ddd":0,"ind":18,"ty":4,"nm":"Steel","sr":1,"ks":{"o":{"a":0,"k":100,"ix":11},"r":{"a":1,"k":[{"i":{"x":[0.91],"y":[1]},"o":{"x":[0.324],"y":[0]},"t":0,"s":[15]},{"i":{"x":[0.34],"y":[1]},"o":{"x":[0.66],"y":[0]},"t":73,"s":[11]},{"t":84,"s":[15]}],"ix":10},"p":{"a":0,"k":[180.312,420.862,0],"ix":2,"l":2},"a":{"a":0,"k":[0,46.875,0],"ix":1,"l":2},"s":{"a":0,"k":[200,200,100],"ix":6,"l":2}},"ao":0,"shapes":[{"ty":"gr","it":[{"ty":"rc","d":1,"s":{"a":0,"k":[4.725,93.75],"ix":2},"p":{"a":0,"k":[0,0],"ix":3},"r":{"a":0,"k":0,"ix":4},"nm":"Rectangle Path 1","mn":"ADBE Vector Shape - Rect","hd":false},{"ty":"st","c":{"a":0,"k":[0,0.388235300779,0.466666668653,1],"ix":3},"o":{"a":0,"k":100,"ix":4},"w":{"a":0,"k":1.897,"ix":5},"lc":1,"lj":1,"ml":10,"bm":0,"nm":"Stroke 1","mn":"ADBE Vector Graphic - Stroke","hd":false},{"ty":"tr","p":{"a":0,"k":[0,0],"ix":2},"a":{"a":0,"k":[0,0],"ix":1},"s":{"a":0,"k":[100,100],"ix":3},"r":{"a":0,"k":0,"ix":6},"o":{"a":0,"k":100,"ix":7},"sk":{"a":0,"k":0,"ix":4},"sa":{"a":0,"k":0,"ix":5},"nm":"Transform"}],"nm":"Steel","np":3,"cix":2,"bm":0,"ix":1,"mn":"ADBE Vector Group","hd":false}],"ip":0,"op":96,"st":0,"ct":1,"bm":0},{"ddd":0,"ind":19,"ty":4,"nm":"Steel 2","sr":1,"ks":{"o":{"a":0,"k":100,"ix":11},"r":{"a":1,"k":[{"i":{"x":[0.91],"y":[1]},"o":{"x":[0.324],"y":[0]},"t":0,"s":[15]},{"i":{"x":[0.34],"y":[1]},"o":{"x":[0.66],"y":[0]},"t":73,"s":[11]},{"t":84,"s":[15]}],"ix":10},"p":{"a":0,"k":[180.312,420.862,0],"ix":2,"l":2},"a":{"a":0,"k":[0,46.875,0],"ix":1,"l":2},"s":{"a":0,"k":[200,200,100],"ix":6,"l":2}},"ao":0,"shapes":[{"ty":"gr","it":[{"ty":"rc","d":1,"s":{"a":0,"k":[4.725,93.75],"ix":2},"p":{"a":0,"k":[0,0],"ix":3},"r":{"a":0,"k":0,"ix":4},"nm":"Rectangle Path 1","mn":"ADBE Vector Shape - Rect","hd":false},{"ty":"st","c":{"a":0,"k":[0,0.388235300779,0.466666668653,1],"ix":3},"o":{"a":0,"k":100,"ix":4},"w":{"a":0,"k":1.897,"ix":5},"lc":1,"lj":1,"ml":10,"bm":0,"nm":"Stroke 1","mn":"ADBE Vector Graphic - Stroke","hd":false},{"ty":"fl","c":{"a":0,"k":[1,1,1,1],"ix":4},"o":{"a":0,"k":100,"ix":5},"r":1,"bm":0,"nm":"Fill 1","mn":"ADBE Vector Graphic - Fill","hd":false},{"ty":"tr","p":{"a":0,"k":[0,0],"ix":2},"a":{"a":0,"k":[0,0],"ix":1},"s":{"a":0,"k":[100,100],"ix":3},"r":{"a":0,"k":0,"ix":6},"o":{"a":0,"k":100,"ix":7},"sk":{"a":0,"k":0,"ix":4},"sa":{"a":0,"k":0,"ix":5},"nm":"Transform"}],"nm":"Steel","np":3,"cix":2,"bm":0,"ix":1,"mn":"ADBE Vector Group","hd":false}],"ip":0,"op":96,"st":0,"ct":1,"bm":0}]}],"layers":[{"ddd":0,"ind":1,"ty":0,"nm":"Lokaal geproduceerd","refId":"comp_0","sr":1,"ks":{"o":{"a":0,"k":100,"ix":11},"r":{"a":0,"k":0,"ix":10},"p":{"a":0,"k":[250,250,0],"ix":2,"l":2},"a":{"a":0,"k":[250,250,0],"ix":1,"l":2},"s":{"a":0,"k":[100,100,100],"ix":6,"l":2}},"ao":0,"w":500,"h":500,"ip":76,"op":96,"st":0,"bm":0},{"ddd":0,"ind":2,"ty":0,"nm":"Lokaal geproduceerd","refId":"comp_0","sr":1,"ks":{"o":{"a":0,"k":100,"ix":11},"r":{"a":0,"k":0,"ix":10},"p":{"a":0,"k":[250,250,0],"ix":2,"l":2},"a":{"a":0,"k":[250,250,0],"ix":1,"l":2},"s":{"a":0,"k":[100,100,100],"ix":6,"l":2}},"ao":0,"w":500,"h":500,"ip":96,"op":172,"st":96,"bm":0}],"markers":[],"props":{}}